Metadata-Version: 2.1
Name: python-zeep
Version: 3.1.0
Summary: A modern/fast Python SOAP client based on lxml / requests
Home-page: http://docs.python-zeep.org
Author: Michael van Tellingen
Author-email: michaelvantellingen@gmail.com
License: MIT
Platform: UNKNOWN
Classifier: Development Status :: 5 - Production/Stable
Classifier: License :: OSI Approved :: MIT License
Classifier: Programming Language :: Python :: 2
Classifier: Programming Language :: Python :: 2.7
Classifier: Programming Language :: Python :: 3
Classifier: Programming Language :: Python :: 3.4
Classifier: Programming Language :: Python :: 3.5
Classifier: Programming Language :: Python :: 3.6
Classifier: Programming Language :: Python :: Implementation :: CPython
Classifier: Programming Language :: Python :: Implementation :: PyPy
Provides-Extra: docs
Provides-Extra: test
Provides-Extra: async
Provides-Extra: tornado
Provides-Extra: xmlsec
Requires-Dist: appdirs (>=1.4.0)
Requires-Dist: attrs (>=17.2.0)
Requires-Dist: cached-property (>=1.3.0)
Requires-Dist: defusedxml (>=0.4.1)
Requires-Dist: isodate (>=0.5.4)
Requires-Dist: lxml (>=3.1.0)
Requires-Dist: requests (>=2.7.0)
Requires-Dist: requests-toolbelt (>=0.7.1)
Requires-Dist: six (>=1.9.0)
Requires-Dist: pytz
Provides-Extra: async
Requires-Dist: aiohttp (>=1.0); extra == 'async'
Provides-Extra: docs
Requires-Dist: sphinx (>=1.4.0); extra == 'docs'
Provides-Extra: test
Requires-Dist: freezegun (==0.3.8); extra == 'test'
Requires-Dist: mock (==2.0.0); extra == 'test'
Requires-Dist: pretend (==1.0.8); extra == 'test'
Requires-Dist: pytest-cov (==2.5.1); extra == 'test'
Requires-Dist: pytest (==3.1.3); extra == 'test'
Requires-Dist: requests-mock (>=0.7.0); extra == 'test'
Requires-Dist: pytest-tornado (==0.4.5); extra == 'test'
Requires-Dist: isort (==4.2.15); extra == 'test'
Requires-Dist: flake8 (==3.3.0); extra == 'test'
Requires-Dist: flake8-blind-except (==0.1.1); extra == 'test'
Requires-Dist: flake8-debugger (==1.4.0); extra == 'test'
Requires-Dist: flake8-imports (==0.1.1); extra == 'test'
Requires-Dist: aioresponses (>=0.4.1); extra == 'test'
Provides-Extra: tornado
Requires-Dist: tornado (<5,>=4.0.2); extra == 'tornado'
Provides-Extra: xmlsec
Requires-Dist: xmlsec (>=0.6.1); extra == 'xmlsec'
